iinuclear/__init__.py
iinuclear/isit.py
iinuclear/plots.py
iinuclear/utils.py
iinuclear/ref_data/reference.txt
iinuclear-0.1.dist-info/METADATA
iinuclear-0.1.dist-info/WHEEL
iinuclear-0.1.dist-info/top_level.txt
iinuclear-0.1.dist-info/RECORD
