Metadata-Version: 2.4
Name: iinuclear
Version: 0.1
Summary: Functions to determine whether a transient is nuclear.
Home-page: https://github.com/gmzsebastian/iinuclear
Author: Sebastian Gomez
Author-email: sebastian.gomez@austin.utexas.edu
License: MIT
Requires-Python: >=3.6
Requires-Dist: numpy
Requires-Dist: matplotlib
Requires-Dist: astropy
Requires-Dist: scipy
Requires-Dist: astroquery
Requires-Dist: emcee
Requires-Dist: alerce
Dynamic: author
Dynamic: author-email
Dynamic: home-page
Dynamic: license
Dynamic: requires-dist
Dynamic: requires-python
Dynamic: summary
